educalingoDictionary/EducalingoDictionary.py
educalingoDictionary/__init__.py
tests/__init__.py
tests/test_educalingo_dictionary.py
educalingoDictionary-0.1.0a0.dist-info/LICENSE
educalingoDictionary-0.1.0a0.dist-info/METADATA
educalingoDictionary-0.1.0a0.dist-info/WHEEL
educalingoDictionary-0.1.0a0.dist-info/top_level.txt
educalingoDictionary-0.1.0a0.dist-info/RECORD
