Metadata-Version: 2.1
Name: educalingoDictionary
Version: 0.1.0a0
Summary: Gets data from the Educalingo dictionary
Home-page: https://github.com/JessicaSousa/EducalingoDictionary
Author: Jessica Sousa
Author-email: jessicacardosops@gmail.com
License: MIT
Keywords: scrapping dictionary
Platform: UNKNOWN
Classifier: Environment :: Console
Classifier: Operating System :: OS Independent
Classifier: Intended Audience :: Developers
Classifier: Intended Audience :: Education
Classifier: Intended Audience :: Other Audience
Classifier: Topic :: Software Development :: Libraries :: Python Modules
Classifier: License :: OSI Approved :: MIT License
Classifier: Programming Language :: Python :: 3.6
Classifier: Programming Language :: Python :: 3.7
Classifier: Programming Language :: Python :: Implementation :: PyPy
Requires-Python: >=3.6
Requires-Dist: requests
Requires-Dist: beautifulsoup4
